src/sparse_coding/__init__.py
src/sparse_coding/batch_processor.py
src/sparse_coding/batch_processor_complete.py
src/sparse_coding/config.py
src/sparse_coding/core.py
src/sparse_coding/dictionary_learning.py
src/sparse_coding/example_visualization_usage.py
src/sparse_coding/fast_coverage_test.py
src/sparse_coding/feature_extraction.py
src/sparse_coding/research_accurate_sparsity.py
src/sparse_coding/simple_test.py
src/sparse_coding/sparse_coder.py
src/sparse_coding/temp_methods.py
src/sparse_coding/utils.py
src/sparse_coding/utils_refactored.py
src/sparse_coding/visualization.py
src/sparse_coding/viz.py
src/sparse_coding/core_modules/__init__.py
src/sparse_coding/core_modules/core_algorithms.py
src/sparse_coding/core_modules/dictionary_updates.py
src/sparse_coding/core_modules/optimization_algorithms.py
src/sparse_coding/core_modules/utilities_validation.py
src/sparse_coding/old_archive/core_original_1546_lines.py
src/sparse_coding/old_archive/sparse_coder_original.py
src/sparse_coding/old_archive_modules/__init__.py
src/sparse_coding/old_archive_modules/core_algorithm.py
src/sparse_coding/old_archive_modules/data_processing.py
src/sparse_coding/old_archive_modules/dictionary_update.py
src/sparse_coding/old_archive_modules/olshausen_field.py
src/sparse_coding/old_archive_modules/optimization.py
src/sparse_coding/old_archive_modules/utilities.py
src/sparse_coding/old_archive_modules/validation.py
src/sparse_coding/old_archive_modules/visualization.py
src/sparse_coding/sc_modules/__init__.py
src/sparse_coding/sc_modules/core_algorithm.py
src/sparse_coding/sc_modules/data_processing.py
src/sparse_coding/sc_modules/dictionary_update.py
src/sparse_coding/sc_modules/olshausen_field.py
src/sparse_coding/sc_modules/optimization.py
src/sparse_coding/sc_modules/utilities.py
src/sparse_coding/sc_modules/validation.py
src/sparse_coding/sc_modules/visualization.py
src/sparse_coding/utils_modules/__init__.py
src/sparse_coding/utils_modules/advanced_specialized.py
sparse_coding-2.3.0.dist-info/METADATA
sparse_coding-2.3.0.dist-info/WHEEL
sparse_coding-2.3.0.dist-info/licenses/LICENSE
sparse_coding-2.3.0.dist-info/RECORD
